warpcode/__init__.py
warpcode/activity_dashboard.py
warpcode/bdd_runner.py
warpcode/claude_interface.py
warpcode/claude_otel_monitor.py
warpcode/cli_dashboard.py
warpcode/complexity_checker.py
warpcode/environment_manager.py
warpcode/main.py
warpcode/orchestrator.py
warpcode/reality_validator.py
warpcode/requirements.txt
warpcode/scoreboard_manager.py
warpcode/setup.py
warpcode/test_claude_realtime.py
warpcode/test_claude_stream.py
warpcode/ascii_art/startup.txt
warpcode-1.1.5.dist-info/METADATA
warpcode-1.1.5.dist-info/WHEEL
warpcode-1.1.5.dist-info/entry_points.txt
warpcode-1.1.5.dist-info/top_level.txt
warpcode-1.1.5.dist-info/RECORD
