Metadata-Version: 2.4
Name: warpcode
Version: 1.1.5
Summary: Warp through development cycles with automated BDD and Claude Coder
Author-email: Claude Code <noreply@anthropic.com>
License: MIT
Project-URL: Homepage, https://github.com/warpcodedev/warpcode
Project-URL: Bug Reports, https://github.com/warpcodedev/warpcode/issues
Project-URL: Source, https://github.com/warpcodedev/warpcode
Project-URL: Documentation, https://github.com/warpcodedev/warpcode#readme
Keywords: bdd,testing,automation,claude,ai,development,orchestration
Classifier: Development Status :: 4 - Beta
Classifier: Intended Audience :: Developers
Classifier: Topic :: Software Development :: Testing
Classifier: Topic :: Software Development :: Code Generators
Classifier: Topic :: Software Development :: Quality Assurance
Classifier: License :: OSI Approved :: MIT License
Classifier: Programming Language :: Python :: 3
Classifier: Programming Language :: Python :: 3.10
Classifier: Programming Language :: Python :: 3.11
Classifier: Programming Language :: Python :: 3.12
Classifier: Environment :: Console
Classifier: Operating System :: OS Independent
Requires-Python: >=3.10
Requires-Dist: behave>=1.2.6
Requires-Dist: questionary>=1.10.0
Requires-Dist: radon>=4.1.0
Requires-Dist: anthropic>=0.25.0
Requires-Dist: rich>=13.0
Requires-Dist: click>=8.0
Requires-Dist: PyYAML>=6.0
Requires-Dist: pexpect>=4.8.0
Requires-Dist: pillow>=9.0.0
Requires-Dist: selenium>=4.0.0
Requires-Dist: webdriver-manager>=3.8.0
